kantan/__init__.py
kantan/__main__.py
kantan/builder.py
kantan/cli.py
kantan-0.4.0.dist-info/LICENSE
kantan-0.4.0.dist-info/METADATA
kantan-0.4.0.dist-info/WHEEL
kantan-0.4.0.dist-info/entry_points.txt
kantan-0.4.0.dist-info/top_level.txt
kantan-0.4.0.dist-info/RECORD
