Metadata-Version: 2.1
Name: kantan
Version: 0.4.0
Summary: Configurable venv extension
Project-URL: homepage, https://github.com/miguelnmiranda/kantan
Requires-Python: <4,>=3.7
License-File: LICENSE
Provides-Extra: dev
Requires-Dist: pytest (==7.1.2) ; extra == 'dev'
Requires-Dist: pytest-cov (==3.0.0) ; extra == 'dev'
Requires-Dist: mock (==4.0.3) ; extra == 'dev'
Requires-Dist: pylint (==2.14.1) ; extra == 'dev'
Requires-Dist: bandit (==1.7.4) ; extra == 'dev'
Requires-Dist: black (==22.3.0) ; extra == 'dev'
Requires-Dist: isort (==5.10.1) ; extra == 'dev'
Requires-Dist: pyright (==1.1.288) ; extra == 'dev'
Requires-Dist: toml (==0.10.2) ; extra == 'dev'
Provides-Extra: pub
Requires-Dist: build (==0.8.0) ; extra == 'pub'
Requires-Dist: twine (==4.0.1) ; extra == 'pub'
